calculator/__init__.py
calculator/ui/cli.py
calculator/ui/gui.py
unibo_dtm_se_calculator-0.1.1.dist-info/entry_points.txt
unibo_dtm_se_calculator-0.1.1.dist-info/LICENSE
unibo_dtm_se_calculator-0.1.1.dist-info/METADATA
unibo_dtm_se_calculator-0.1.1.dist-info/WHEEL
unibo_dtm_se_calculator-0.1.1.dist-info/RECORD
