Metadata-Version: 2.1
Name: unibo-dtm-se-calculator
Version: 0.1.1
Summary: A simple calculator toolkit written in Python, with several UIs. It is part of the Software Engineering course at the University of Bologna.
License: Apache 2.0
Author: Giovanni Ciatto
Author-email: giovanni.ciatto@unibo.it
Requires-Python: >=3.10.0,<4.0.0
Classifier: License :: Other/Proprietary License
Classifier: Programming Language :: Python :: 3
Classifier: Programming Language :: Python :: 3.10
Classifier: Programming Language :: Python :: 3.11
Classifier: Programming Language :: Python :: 3.12
Requires-Dist: Kivy (>=2.3.0,<3.0.0)
